ipo_india/__init__.py
ipo_india/ipo.py
ipo_india/ipo_scraper.py
ipo_india/main.py
ipo_india/test_code.py
ipo_india-0.0.12.dist-info/METADATA
ipo_india-0.0.12.dist-info/WHEEL
ipo_india-0.0.12.dist-info/top_level.txt
ipo_india-0.0.12.dist-info/RECORD
