Metadata-Version: 2.1
Name: ipo-india
Version: 0.0.12
Summary: UNKNOWN
Home-page: https://github.com/MichaelKim0407/tutorial-pip-package
Author: Aman Agarwal
Author-email: aman.agarwal150@gmail.com
License: UNKNOWN
Platform: UNKNOWN
Requires-Python: >=3.9
Requires-Dist: beautifulsoup4 (==4.12.2)
Requires-Dist: bs4 (==0.0.1)
Requires-Dist: html5lib (==1.1)
Requires-Dist: pydantic (==1.10.7)
Requires-Dist: pytz (==2023.3)
Requires-Dist: requests (==2.30.0)
